oasis_tui/__init__.py
oasis_tui/tui.py
oasis_tui-1.0.2.dist-info/licenses/LICENSE
oasis_tui-1.0.2.dist-info/METADATA
oasis_tui-1.0.2.dist-info/WHEEL
oasis_tui-1.0.2.dist-info/entry_points.txt
oasis_tui-1.0.2.dist-info/top_level.txt
oasis_tui-1.0.2.dist-info/RECORD
