Metadata-Version: 2.4
Name: oasis-tui
Version: 1.0.2
Summary: TUI for the Open Acquisition System for IEPE Sensors (OASIS)
Author-email: Johannes Maierhofer <j.maierhofer@tum.de>, Oliver Zobel <oliver.zobel@tum.de>
Project-URL: Homepage, https://gitlab.com/oasis-acquisition/oasis-tui
Classifier: Development Status :: 4 - Beta
Classifier: Environment :: Console
Classifier: Intended Audience :: Science/Research
Classifier: Intended Audience :: Developers
Classifier: License :: OSI Approved :: MIT License
Classifier: Operating System :: OS Independent
Classifier: Programming Language :: Python :: 3
Classifier: Programming Language :: Python :: 3.11
Classifier: Programming Language :: Python :: 3.12
Classifier: Topic :: Scientific/Engineering
Classifier: Topic :: Software Development :: User Interfaces
Classifier: Topic :: Terminals
Requires-Python: >=3.11
License-File: LICENSE
Requires-Dist: oasis-api
Requires-Dist: pyserial
Requires-Dist: questionary
Requires-Dist: h5py
Dynamic: license-file
